<?xml version="1.0"?>
<beer id="Three-Floyds-Brewing/Deesko" brewery_id="Three-Floyds-Brewing" abv="3" ibu="10">
  <name>Deesko</name>
  <description>Our take on a traditional Berliner weiss. A slightly tart and refreshing wheat beer, low in alcohol and often served with a flavored syrup. Ask your server for our current flavors.</description>
  <availability>year-round</availability>
  <ingredients/>
  <grains/>
  <grains/>
  <hops/>
  <yeast/>
  <otherings/>
  <styles>
    <style>Weiss</style>
  </styles>
</beer>
