<?xml version="1.0" encoding="UTF-8"?>
<beer>
  <id>Saranac/Black-Diamond-Bock</id>
  <brewery_id>Saranac</brewery_id>
  <abv>6</abv>
  <name>Black Diamond Bock</name>
  <description>Saranac Black Diamond Bock is a rich, malty brew, made with traditional German malts and hops and fermented with a lager yeast. Aged for months for a rich but smooth malty taste. A nice reward for enduring your winter months.</description>
  <availability>seasonal</availability>
  <ingredients/>
  <grains>Munich, Vienna</grains>
  <grains>Munich, Vienna</grains>
  <hops>Hallertau</hops>
  <yeast/>
  <otherings/>
  <styles>
    <style><name>Traditional Bock</name></style>
  </styles>
</beer>
