<?xml version="1.0" encoding="UTF-8"?>
<beer>
  <id>Summit-Brewing/Extra-Special-Bitter</id>
  <brewery_id>Summit-Brewing</brewery_id>
  <abv>5.1</abv>
  <ibu>50</ibu>
  <name>Extra Special Bitter</name>
  <description>A recent addition to our line of ales -- it shares the character of the English bitters of old, with added Summit uniqueness.  The dark amber color and rich taste make Summit ESB wonderfully distinctive.</description>
  <availability>year-round</availability>
  <ingredients/>
  <grains>2-row harrington, golden promise, maris otter, and crystal medium</grains>
  <grains>2-row harrington, golden promise, maris otter, and crystal medium</grains>
  <hops>fuggle, target and northdown</hops>
  <yeast/>
  <otherings/>
  <styles>
    <style>ESB</style>
  </styles>
</beer>
