<?xml version="1.0" encoding="UTF-8"?>
<beer>
  <id>Summit-Brewing/Great-Norther-Porter</id>
  <brewery_id>Summit-Brewing</brewery_id>
  <abv>5.6</abv>
  <ibu>50</ibu>
  <name>Great Norther Porter</name>
  <description/>
  <availability>year-round</availability>
  <ingredients/>
  <grains>2-row harrington, caramel, carafa II</grains>
  <grains>2-row harrington, caramel, carafa II</grains>
  <hops>horizon, fuggle, cascade</hops>
  <yeast/>
  <otherings/>
  <styles>
    <style><name>Poter</name></style>
  </styles>
</beer>
