<?xml version="1.0"?>
<place id="BJs-Restaurant-and-Brewery-Brea-California" in_operation="yes" specializes_in_beer="yes" tied="no" bottled_beer_to_go="no" growlers_to_go="no" kegs_to_go="no" brew_on_premises="yes" taps="" casks="" bottles="" wheelchair_accessible="" music="" wifi="">
  <type>Brewpub</type>
  <name>BJ's Restaurant &amp; Brewery</name>
  <description/>
  <phone>(714) 990-2095</phone>
  <uri>http://www.bjsrestaurants.com/</uri>
  <established/>
  <address>
    <street>600 Brea Mall Drive</street>
    <city>Brea</city>
    <state>California</state>
    <neighborhood/>
    <zip>92821-5764</zip>
    <latitude>33.913603</latitude>
    <longitude>-117.889223</longitude>
    <country>US</country>
  </address>
  <hours>
    <open/>
    <tour/>
    <tasting/>
  </hours>
  <tour_info/>
  <restaurant reservations="" alcohol="" accepts_credit_cards="" good_for_groups="" outdoor_seating="" smoking="">
    <food_description/>
    <menu_uri/>
    <price_range/>
    <attire/>
    <waiter_service>
</waiter_service>
  </restaurant>
  <parking/>
  <kid_friendly/>
</place>
