<?xml version="1.0"?>
<place id="Karl-Strauss-Brewery-Restaurant-Carlsbad-Carlsbad-California" in_operation="yes" specializes_in_beer="yes" tied="no" bottled_beer_to_go="no" growlers_to_go="no" kegs_to_go="no" brew_on_premises="no" taps="" casks="" bottles="" wheelchair_accessible="" music="" wifi="">
  <type>Bar</type>
  <name>Karl Strauss Brewery Restaurant, Carlsbad</name>
  <description/>
  <phone>(760) 431-2739</phone>
  <uri>http://www.karlstrauss.com/</uri>
  <established/>
  <address>
    <street>5801 Armada Dr</street>
    <city>Carlsbad</city>
    <state>California</state>
    <neighborhood/>
    <zip>92008-4609</zip>
    <latitude>33.125004</latitude>
    <longitude>-117.314451</longitude>
    <country>US</country>
  </address>
  <hours>
    <open/>
    <tour/>
    <tasting/>
  </hours>
  <tour_info/>
  <restaurant reservations="" alcohol="" accepts_credit_cards="" good_for_groups="" outdoor_seating="" smoking="">
    <food_description/>
    <menu_uri/>
    <price_range/>
    <attire/>
    <waiter_service>
</waiter_service>
  </restaurant>
  <parking/>
  <kid_friendly/>
</place>
