<?xml version="1.0" encoding="UTF-8"?>
<place>
  <id>Thirsty-Bear-Brewing-Company-San-Francisco-California</id>
  <in_operation>yes</in_operation>
  <specializes_in_beer>yes</specializes_in_beer>
  <tied>no</tied>
  <bottled_beer_to_go>no</bottled_beer_to_go>
  <growlers_to_go>no</growlers_to_go>
  <kegs_to_go>no</kegs_to_go>
  <brew_on_premises>yes</brew_on_premises>
  <taps/>
  <casks/>
  <bottles/>
  <wheelchair_accessible/>
  <music/>
  <wifi/>
  <type>Brewpub</type>
  <name>Thirsty Bear Brewing Company</name>
  <description/>
  <phone>(415) 974-0905</phone>
  <uri>http://www.thirstybear.com/</uri>
  <established/>
  <address>
    <street>661 Howard Street</street>
    <city>San Francisco</city>
    <state>California</state>
    <neighborhood/>
    <zip>94105-3915</zip>
    <latitude>37.785552</latitude>
    <longitude>-122.399568</longitude>
    <country>US</country>
  </address>
  <hours>
    <open/>
    <tour/>
    <tasting/>
  </hours>
  <tour_info/>
  <restaurant>
    <reservations/>
    <alcohol/>
    <accepts_credit_cards/>
    <good_for_groups/>
    <outdoor_seating/>
    <smoking/>
    <food_description/>
    <menu_uri/>
    <price_range/>
    <attire/>
    <waiter_service>
</waiter_service>
  </restaurant>
  <parking/>
  <kid_friendly/>
</place>
